setup.cfg
setup.py
pydisconf/__init__.py
pydisconf.egg-info/PKG-INFO
pydisconf.egg-info/SOURCES.txt
pydisconf.egg-info/dependency_links.txt
pydisconf.egg-info/top_level.txt