Metadata-Version: 1.1
Name: pydisconf
Version: 0.1.5.dev1
Summary: Python client of disconf
Home-page: https://github.com/sillyemperor/pydisconf
Author: Wang Jiang
Author-email: sillyemperor@163.com
License: MIT
Keywords: configure Disconfig
Platform: UNKNOWN
Classifier: Development Status :: 1 - Planning
Classifier: Intended Audience :: Developers
Classifier: Topic :: Software Development :: Libraries
Classifier: License :: OSI Approved :: MIT License
Classifier: Programming Language :: Python :: 2
Classifier: Programming Language :: Python :: 2.7
